quickutil4py/__init__.py
quickutil4py/datetime_util.py
quickutil4py/db_util.py
quickutil4py/file_util.py
quickutil4py-0.1.dist-info/LICENSE
quickutil4py-0.1.dist-info/METADATA
quickutil4py-0.1.dist-info/WHEEL
quickutil4py-0.1.dist-info/top_level.txt
quickutil4py-0.1.dist-info/RECORD
