Metadata-Version: 2.1
Name: quickutil4py
Version: 0.1
Summary: Some general python tools
Home-page: https://github.com/jumpingcoder/quickutil4py
Author: FF Miao
Author-email: miaofeifan@foxmail.com
License: MIT
Classifier: Development Status :: 3 - Alpha
Classifier: Intended Audience :: Developers
Classifier: License :: OSI Approved :: MIT License
Classifier: Programming Language :: Python :: 3
Classifier: Programming Language :: Python :: 3.6
Classifier: Programming Language :: Python :: 3.7
Classifier: Programming Language :: Python :: 3.8
Classifier: Programming Language :: Python :: 3.9
Classifier: Programming Language :: Python :: 3.10
Classifier: Topic :: Software Development :: Libraries :: Python Modules
License-File: LICENSE
Requires-Dist: pgmysql
Requires-Dist: dbutils
